{"_id":"redis-parser","_rev":"24-976e3a0c2d4db5d2d8409de495702d43","name":"redis-parser","description":"Javascript Redis protocol (RESP) parser","dist-tags":{"latest":"3.0.0"},"versions":{"0.0.1":{"name":"redis-parser","version":"0.0.1","description":"Javascript Redis protocol (RESP) parser","main":"index.js","scripts":{"test":"test"},"repository":{"type":"git","url":"git+https://github.com/NodeRedis/node-redis-parser.git"},"keywords":["redis","protocol","parser","database","javascript","node"],"author":{"name":"Ruben Bridgewater"},"license":"MIT","bugs":{"url":"https://github.com/NodeRedis/node-redis-parser/issues"},"homepage":"https://github.com/NodeRedis/node-redis-parser#readme","gitHead":"580e4c392850f8dd568529dea3c897acb3ab9fbd","_id":"redis-parser@0.0.1","_shasum":"287c6d739107edebc621463882a68227fd4de70f","_from":".","_npmVersion":"2.14.7","_nodeVersion":"4.2.1","_npmUser":{"name":"bridgear","email":"ruben@bridgewater.de"},"dist":{"shasum":"287c6d739107edebc621463882a68227fd4de70f","tarball":"https://registry.npmjs.org/redis-parser/-/redis-parser-0.0.1.tgz"},"maintainers":[{"name":"bridgear","email":"ruben@bridgewater.de"}],"directories":{}},"1.0.0":{"name":"redis-parser","version":"1.0.0","description":"Javascript Redis protocol (RESP) parser","main":"index.js","scripts":{"test":"mocha","posttest":"jshint . && npm run coverage && npm run coverage:check","coverage":"node ./node_modules/istanbul/lib/cli.js cover --preserve-comments ./node_modules/mocha/bin/_mocha -- -R spec","coverage:check":"node ./node_modules/istanbul/lib/cli.js check-coverage --branch 100 --statement 100"},"repository":{"type":"git","url":"git+https://github.com/NodeRedis/node-redis-parser.git"},"keywords":["redis","protocol","parser","database","javascript","node","nodejs","resp","hiredis"],"engines":{"node":">=0.10.0"},"devDependencies":{"jshint":"^2.8.0","mocha":"^2.3.2","istanbul":"^0.4.0","codeclimate-test-reporter":"^0.1.1"},"optionalDependency":{"hiredis":"^0.4.1"},"author":{"name":"Ruben Bridgewater"},"license":"MIT","bugs":{"url":"https://github.com/NodeRedis/node-redis-parser/issues"},"homepage":"https://github.com/NodeRedis/node-redis-parser#readme","directories":{"test":"test","lib":"lib"},"gitHead":"af7d9d454aa9a7e47d9a33f51a3d8ff505055484","_id":"redis-parser@1.0.0","_shasum":"0b309702182413512c22f8e2714aa3eb12b5bfaf","_from":".","_npmVersion":"2.14.7","_nodeVersion":"4.2.2","_npmUser":{"name":"bridgear","email":"ruben@bridgewater.de"},"dist":{"shasum":"0b309702182413512c22f8e2714aa3eb12b5bfaf","tarball":"https://registry.npmjs.org/redis-parser/-/redis-parser-1.0.0.tgz"},"maintainers":[{"name":"bridgear","email":"ruben@bridgewater.de"}]},"1.1.0":{"name":"redis-parser","version":"1.1.0","description":"Javascript Redis protocol (RESP) parser","main":"index.js","scripts":{"test":"mocha","posttest":"jshint . && npm run coverage && npm run coverage:check","coverage":"node ./node_modules/istanbul/lib/cli.js cover --preserve-comments ./node_modules/mocha/bin/_mocha -- -R spec","coverage:check":"node ./node_modules/istanbul/lib/cli.js check-coverage --branch 100 --statement 100"},"repository":{"type":"git","url":"git+https://github.com/NodeRedis/node-redis-parser.git"},"keywords":["redis","protocol","parser","database","javascript","node","nodejs","resp","hiredis"],"engines":{"node":">=0.10.0"},"devDependencies":{"jshint":"^2.8.0","mocha":"^2.3.2","istanbul":"^0.4.0","codeclimate-test-reporter":"^0.1.1"},"optionalDependency":{"hiredis":"^0.4.1"},"author":{"name":"Ruben Bridgewater"},"license":"MIT","bugs":{"url":"https://github.com/NodeRedis/node-redis-parser/issues"},"homepage":"https://github.com/NodeRedis/node-redis-parser#readme","directories":{"test":"test","lib":"lib"},"gitHead":"56bf8827a6cb3d676ba9305c20c707edf836b719","_id":"redis-parser@1.1.0","_shasum":"62cc81a1c8cb78434e766f99eae6034763ddd234","_from":".","_npmVersion":"2.14.12","_nodeVersion":"4.2.6","_npmUser":{"name":"bridgear","email":"ruben@bridgewater.de"},"dist":{"shasum":"62cc81a1c8cb78434e766f99eae6034763ddd234","tarball":"https://registry.npmjs.org/redis-parser/-/redis-parser-1.1.0.tgz"},"maintainers":[{"name":"bridgear","email":"ruben@bridgewater.de"}]},"1.2.0":{"name":"redis-parser","version":"1.2.0","description":"Javascript Redis protocol (RESP) parser","main":"index.js","scripts":{"test":"mocha","posttest":"jshint . && npm run coverage && npm run coverage:check","coverage":"node ./node_modules/istanbul/lib/cli.js cover --preserve-comments ./node_modules/mocha/bin/_mocha -- -R spec","coverage:check":"node ./node_modules/istanbul/lib/cli.js check-coverage --branch 100 --statement 100"},"repository":{"type":"git","url":"git+https://github.com/NodeRedis/node-redis-parser.git"},"keywords":["redis","protocol","parser","database","javascript","node","nodejs","resp","hiredis"],"engines":{"node":">=0.10.0"},"devDependencies":{"codeclimate-test-reporter":"^0.1.1","intercept-stdout":"^0.1.2","istanbul":"^0.4.0","jshint":"^2.8.0","mocha":"^2.3.2"},"optionalDependency":{"hiredis":"^0.4.1"},"author":{"name":"Ruben Bridgewater"},"license":"MIT","bugs":{"url":"https://github.com/NodeRedis/node-redis-parser/issues"},"homepage":"https://github.com/NodeRedis/node-redis-parser#readme","directories":{"test":"test","lib":"lib"},"gitHead":"b749f3e0aa949b5dae3cb36d31f63fc98f3be895","_id":"redis-parser@1.2.0","_shasum":"953c4a810fb5088d2ec07d77f72dba7b99b522bb","_from":".","_npmVersion":"2.14.12","_nodeVersion":"4.2.6","_npmUser":{"name":"bridgear","email":"ruben@bridgewater.de"},"dist":{"shasum":"953c4a810fb5088d2ec07d77f72dba7b99b522bb","tarball":"https://registry.npmjs.org/redis-parser/-/redis-parser-1.2.0.tgz"},"maintainers":[{"name":"bridgear","email":"ruben@bridgewater.de"}],"_npmOperationalInternal":{"host":"packages-12-west.internal.npmjs.com","tmp":"tmp/redis-parser-1.2.0.tgz_1459039714642_0.9321969968732446"}},"1.3.0":{"name":"redis-parser","version":"1.3.0","description":"Javascript Redis protocol (RESP) parser","main":"index.js","scripts":{"test":"mocha","posttest":"jshint . && npm run coverage && npm run coverage:check","coverage":"node ./node_modules/istanbul/lib/cli.js cover --preserve-comments ./node_modules/mocha/bin/_mocha -- -R spec","coverage:check":"node ./node_modules/istanbul/lib/cli.js check-coverage --branch 100 --statement 100"},"repository":{"type":"git","url":"git+https://github.com/NodeRedis/node-redis-parser.git"},"keywords":["redis","protocol","parser","database","javascript","node","nodejs","resp","hiredis"],"engines":{"node":">=0.10.0"},"devDependencies":{"codeclimate-test-reporter":"^0.1.1","intercept-stdout":"^0.1.2","istanbul":"^0.4.0","jshint":"^2.8.0","mocha":"^2.3.2"},"optionalDependency":{"hiredis":"^0.4.1"},"author":{"name":"Ruben Bridgewater"},"license":"MIT","bugs":{"url":"https://github.com/NodeRedis/node-redis-parser/issues"},"homepage":"https://github.com/NodeRedis/node-redis-parser#readme","directories":{"test":"test","lib":"lib"},"gitHead":"83e383215558212e36a7928ee07059b8f1285ad4","_id":"redis-parser@1.3.0","_shasum":"806ebe7bbfb7d34e4d7c1e9ef282efcfad04126a","_from":".","_npmVersion":"2.14.12","_nodeVersion":"4.2.6","_npmUser":{"name":"bridgear","email":"ruben@bridgewater.de"},"dist":{"shasum":"806ebe7bbfb7d34e4d7c1e9ef282efcfad04126a","tarball":"https://registry.npmjs.org/redis-parser/-/redis-parser-1.3.0.tgz"},"maintainers":[{"name":"bridgear","email":"ruben@bridgewater.de"}],"_npmOperationalInternal":{"host":"packages-12-west.internal.npmjs.com","tmp":"tmp/redis-parser-1.3.0.tgz_1459079154649_0.6692150828894228"}},"2.0.0":{"name":"redis-parser","version":"2.0.0","description":"Javascript Redis protocol (RESP) parser","main":"index.js","scripts":{"test":"npm run coverage","benchmark":"node ./benchmark","posttest":"standard && npm run coverage:check","coverage":"node ./node_modules/istanbul/lib/cli.js cover --preserve-comments ./node_modules/mocha/bin/_mocha -- -R spec","coverage:check":"node ./node_modules/istanbul/lib/cli.js check-coverage --branch 100 --statement 100"},"repository":{"type":"git","url":"git+https://github.com/NodeRedis/node-redis-parser.git"},"keywords":["redis","protocol","parser","database","javascript","node","nodejs","resp","hiredis"],"engines":{"node":">=0.10.0"},"devDependencies":{"benchmark":"^2.1.0","codeclimate-test-reporter":"^0.3.1","intercept-stdout":"^0.1.2","istanbul":"^0.4.0","standard":"^7.0.1","mocha":"^2.3.2","hiredis":"^0.4.1"},"author":{"name":"Ruben Bridgewater"},"license":"MIT","bugs":{"url":"https://github.com/NodeRedis/node-redis-parser/issues"},"homepage":"https://github.com/NodeRedis/node-redis-parser#readme","directories":{"test":"test","lib":"lib"},"gitHead":"c7d974f71f58c394c1711e1c3a934fd49ac80998","_id":"redis-parser@2.0.0","_shasum":"4e353bbedce390e705e8ef29c118f7f18457b953","_from":".","_npmVersion":"2.15.1","_nodeVersion":"4.4.3","_npmUser":{"name":"bridgear","email":"ruben@bridgewater.de"},"dist":{"shasum":"4e353bbedce390e705e8ef29c118f7f18457b953","tarball":"https://registry.npmjs.org/redis-parser/-/redis-parser-2.0.0.tgz"},"maintainers":[{"name":"bridgear","email":"ruben@bridgewater.de"}],"_npmOperationalInternal":{"host":"packages-12-west.internal.npmjs.com","tmp":"tmp/redis-parser-2.0.0.tgz_1464477187747_0.1461840698029846"},"deprecated":"Critical bug fixed in v.2.0.1"},"2.0.1":{"name":"redis-parser","version":"2.0.1","description":"Javascript Redis protocol (RESP) parser","main":"index.js","scripts":{"test":"npm run coverage","benchmark":"node ./benchmark","posttest":"standard && npm run coverage:check","coverage":"node ./node_modules/istanbul/lib/cli.js cover --preserve-comments ./node_modules/mocha/bin/_mocha -- -R spec","coverage:check":"node ./node_modules/istanbul/lib/cli.js check-coverage --branch 100 --statement 100"},"repository":{"type":"git","url":"git+https://github.com/NodeRedis/node-redis-parser.git"},"keywords":["redis","protocol","parser","database","javascript","node","nodejs","resp","hiredis"],"engines":{"node":">=0.10.0"},"devDependencies":{"benchmark":"^2.1.0","codeclimate-test-reporter":"^0.3.1","intercept-stdout":"^0.1.2","istanbul":"^0.4.0","standard":"^7.0.1","mocha":"^2.3.2","hiredis":"^0.4.1"},"author":{"name":"Ruben Bridgewater"},"license":"MIT","bugs":{"url":"https://github.com/NodeRedis/node-redis-parser/issues"},"homepage":"https://github.com/NodeRedis/node-redis-parser#readme","directories":{"test":"test","lib":"lib"},"gitHead":"22fab6d217fc477736563f78103ed27983869b16","_id":"redis-parser@2.0.1","_shasum":"fdd798750335caef7eb85f5d47fd1fc2d3bd2ce9","_from":".","_npmVersion":"2.15.5","_nodeVersion":"4.4.5","_npmUser":{"name":"bridgear","email":"ruben@bridgewater.de"},"dist":{"shasum":"fdd798750335caef7eb85f5d47fd1fc2d3bd2ce9","tarball":"https://registry.npmjs.org/redis-parser/-/redis-parser-2.0.1.tgz"},"maintainers":[{"name":"bridgear","email":"ruben@bridgewater.de"}],"_npmOperationalInternal":{"host":"packages-16-east.internal.npmjs.com","tmp":"tmp/redis-parser-2.0.1.tgz_1465090852051_0.9554107019212097"},"deprecated":"Critical bug fixed in v.2.0.2"},"2.0.2":{"name":"redis-parser","version":"2.0.2","description":"Javascript Redis protocol (RESP) parser","main":"index.js","scripts":{"test":"npm run coverage","benchmark":"node ./benchmark","posttest":"standard && npm run coverage:check","coverage":"node ./node_modules/istanbul/lib/cli.js cover --preserve-comments ./node_modules/mocha/bin/_mocha -- -R spec","coverage:check":"node ./node_modules/istanbul/lib/cli.js check-coverage --branch 100 --statement 100"},"repository":{"type":"git","url":"git+https://github.com/NodeRedis/node-redis-parser.git"},"keywords":["redis","protocol","parser","database","javascript","node","nodejs","resp","hiredis"],"engines":{"node":">=0.10.0"},"devDependencies":{"benchmark":"^2.1.0","codeclimate-test-reporter":"^0.3.1","intercept-stdout":"^0.1.2","istanbul":"^0.4.0","standard":"^7.0.1","mocha":"^2.3.2","hiredis":"^0.4.1"},"author":{"name":"Ruben Bridgewater"},"license":"MIT","bugs":{"url":"https://github.com/NodeRedis/node-redis-parser/issues"},"homepage":"https://github.com/NodeRedis/node-redis-parser#readme","directories":{"test":"test","lib":"lib"},"gitHead":"9f8f1990d426055bf22335cd346af72f105c8146","_id":"redis-parser@2.0.2","_shasum":"c3354d6afef91c90ab941533d8033eb7e7dc5b56","_from":".","_npmVersion":"2.15.0","_nodeVersion":"0.10.44","_npmUser":{"name":"bridgear","email":"ruben@bridgewater.de"},"dist":{"shasum":"c3354d6afef91c90ab941533d8033eb7e7dc5b56","tarball":"https://registry.npmjs.org/redis-parser/-/redis-parser-2.0.2.tgz"},"maintainers":[{"name":"bridgear","email":"ruben@bridgewater.de"}],"_npmOperationalInternal":{"host":"packages-12-west.internal.npmjs.com","tmp":"tmp/redis-parser-2.0.2.tgz_1465393852830_0.8080592304468155"}},"2.0.3":{"name":"redis-parser","version":"2.0.3","description":"Javascript Redis protocol (RESP) parser","main":"index.js","scripts":{"test":"npm run coverage","benchmark":"node ./benchmark","posttest":"standard && npm run coverage:check","coverage":"node ./node_modules/istanbul/lib/cli.js cover --preserve-comments ./node_modules/mocha/bin/_mocha -- -R spec","coverage:check":"node ./node_modules/istanbul/lib/cli.js check-coverage --branch 100 --statement 100"},"repository":{"type":"git","url":"git+https://github.com/NodeRedis/node-redis-parser.git"},"keywords":["redis","protocol","parser","database","javascript","node","nodejs","resp","hiredis"],"engines":{"node":">=0.10.0"},"devDependencies":{"benchmark":"^2.1.0","codeclimate-test-reporter":"^0.3.1","intercept-stdout":"^0.1.2","istanbul":"^0.4.0","standard":"^7.0.1","mocha":"^2.3.2","hiredis":"^0.5.0"},"author":{"name":"Ruben Bridgewater"},"license":"MIT","bugs":{"url":"https://github.com/NodeRedis/node-redis-parser/issues"},"homepage":"https://github.com/NodeRedis/node-redis-parser#readme","directories":{"test":"test","lib":"lib"},"gitHead":"6d7e3feb68fd2b4fedab4b1f17e61485845b01b7","_id":"redis-parser@2.0.3","_shasum":"0d6251b7e5abec4f6050d5e5b0b5f01a578b652e","_from":".","_npmVersion":"2.15.5","_nodeVersion":"4.4.5","_npmUser":{"name":"bridgear","email":"ruben@bridgewater.de"},"dist":{"shasum":"0d6251b7e5abec4f6050d5e5b0b5f01a578b652e","tarball":"https://registry.npmjs.org/redis-parser/-/redis-parser-2.0.3.tgz"},"maintainers":[{"name":"bridgear","email":"ruben@bridgewater.de"}],"_npmOperationalInternal":{"host":"packages-16-east.internal.npmjs.com","tmp":"tmp/redis-parser-2.0.3.tgz_1466151247873_0.8596742362715304"}},"2.0.4":{"name":"redis-parser","version":"2.0.4","description":"Javascript Redis protocol (RESP) parser","main":"index.js","scripts":{"test":"npm run coverage","benchmark":"node ./benchmark","posttest":"standard && npm run coverage:check","coverage":"node ./node_modules/istanbul/lib/cli.js cover --preserve-comments ./node_modules/mocha/bin/_mocha -- -R spec","coverage:check":"node ./node_modules/istanbul/lib/cli.js check-coverage --branch 100 --statement 100"},"repository":{"type":"git","url":"git+https://github.com/NodeRedis/node-redis-parser.git"},"keywords":["redis","protocol","parser","database","javascript","node","nodejs","resp","hiredis"],"engines":{"node":">=0.10.0"},"devDependencies":{"benchmark":"^2.1.0","codeclimate-test-reporter":"^0.3.1","intercept-stdout":"^0.1.2","istanbul":"^0.4.0","standard":"^7.0.1","mocha":"^2.3.2","hiredis":"^0.5.0"},"author":{"name":"Ruben Bridgewater"},"license":"MIT","bugs":{"url":"https://github.com/NodeRedis/node-redis-parser/issues"},"homepage":"https://github.com/NodeRedis/node-redis-parser#readme","directories":{"test":"test","lib":"lib"},"gitHead":"926d8c620722a68f81b4969040142e20bfadb062","_id":"redis-parser@2.0.4","_shasum":"70cbbb3cef8bf41a315388afe14904a65a7a1028","_from":".","_npmVersion":"2.15.8","_nodeVersion":"4.4.7","_npmUser":{"name":"bridgear","email":"ruben@bridgewater.de"},"dist":{"shasum":"70cbbb3cef8bf41a315388afe14904a65a7a1028","tarball":"https://registry.npmjs.org/redis-parser/-/redis-parser-2.0.4.tgz"},"maintainers":[{"name":"bridgear","email":"ruben@bridgewater.de"}],"_npmOperationalInternal":{"host":"packages-12-west.internal.npmjs.com","tmp":"tmp/redis-parser-2.0.4.tgz_1469117535256_0.6028041366953403"}},"2.1.0":{"name":"redis-parser","version":"2.1.0","description":"Javascript Redis protocol (RESP) parser","main":"index.js","scripts":{"test":"npm run coverage","benchmark":"node ./benchmark","posttest":"standard && npm run coverage:check","coverage":"node ./node_modules/istanbul/lib/cli.js cover --preserve-comments ./node_modules/mocha/bin/_mocha -- -R spec","coverage:check":"node ./node_modules/istanbul/lib/cli.js check-coverage --branch 100 --statement 100"},"repository":{"type":"git","url":"git+https://github.com/NodeRedis/node-redis-parser.git"},"keywords":["redis","protocol","parser","database","javascript","node","nodejs","resp","hiredis"],"engines":{"node":">=0.10.0"},"devDependencies":{"benchmark":"^2.1.0","codeclimate-test-reporter":"^0.4.0","intercept-stdout":"^0.1.2","istanbul":"^0.4.0","standard":"^8.5.0","mocha":"^3.1.2","hiredis":"^0.5.0"},"author":{"name":"Ruben Bridgewater"},"license":"MIT","bugs":{"url":"https://github.com/NodeRedis/node-redis-parser/issues"},"homepage":"https://github.com/NodeRedis/node-redis-parser#readme","directories":{"test":"test","lib":"lib"},"gitHead":"8ced1f503a02f59c798902dce239bb14102fadea","_id":"redis-parser@2.1.0","_shasum":"374f5ab9ee38c757bbb917dcc05240c1cfa6c01f","_from":".","_npmVersion":"3.10.8","_nodeVersion":"6.8.0","_npmUser":{"name":"bridgear","email":"ruben@bridgewater.de"},"dist":{"shasum":"374f5ab9ee38c757bbb917dcc05240c1cfa6c01f","tarball":"https://registry.npmjs.org/redis-parser/-/redis-parser-2.1.0.tgz"},"maintainers":[{"name":"bridgear","email":"ruben@bridgewater.de"}],"_npmOperationalInternal":{"host":"packages-18-east.internal.npmjs.com","tmp":"tmp/redis-parser-2.1.0.tgz_1477849124653_0.9786732476204634"}},"2.1.1":{"name":"redis-parser","version":"2.1.1","description":"Javascript Redis protocol (RESP) parser","main":"index.js","scripts":{"test":"npm run coverage","benchmark":"node ./benchmark","posttest":"standard && npm run coverage:check","coverage":"node ./node_modules/istanbul/lib/cli.js cover --preserve-comments ./node_modules/mocha/bin/_mocha -- -R spec","coverage:check":"node ./node_modules/istanbul/lib/cli.js check-coverage --branch 100 --statement 100"},"repository":{"type":"git","url":"git+https://github.com/NodeRedis/node-redis-parser.git"},"keywords":["redis","protocol","parser","database","javascript","node","nodejs","resp","hiredis"],"engines":{"node":">=0.10.0"},"devDependencies":{"benchmark":"^2.1.0","codeclimate-test-reporter":"^0.4.0","intercept-stdout":"^0.1.2","istanbul":"^0.4.0","standard":"^8.5.0","mocha":"^3.1.2","hiredis":"^0.5.0"},"author":{"name":"Ruben Bridgewater"},"license":"MIT","bugs":{"url":"https://github.com/NodeRedis/node-redis-parser/issues"},"homepage":"https://github.com/NodeRedis/node-redis-parser#readme","directories":{"test":"test","lib":"lib"},"gitHead":"85c49dcd20aa9e91099b8b7839049e43871f6019","_id":"redis-parser@2.1.1","_shasum":"80240272ce7dba0bd43152dc716d29134b2625bb","_from":".","_npmVersion":"2.15.0","_nodeVersion":"0.10.44","_npmUser":{"name":"bridgear","email":"ruben@bridgewater.de"},"dist":{"shasum":"80240272ce7dba0bd43152dc716d29134b2625bb","tarball":"https://registry.npmjs.org/redis-parser/-/redis-parser-2.1.1.tgz"},"maintainers":[{"name":"bridgear","email":"ruben@bridgewater.de"}],"_npmOperationalInternal":{"host":"packages-12-west.internal.npmjs.com","tmp":"tmp/redis-parser-2.1.1.tgz_1477919687186_0.8296072955708951"}},"2.2.0":{"name":"redis-parser","version":"2.2.0","description":"Javascript Redis protocol (RESP) parser","main":"index.js","scripts":{"test":"npm run coverage","benchmark":"node ./benchmark","posttest":"standard && npm run coverage:check","coverage":"node ./node_modules/istanbul/lib/cli.js cover --preserve-comments ./node_modules/mocha/bin/_mocha -- -R spec","coverage:check":"node ./node_modules/istanbul/lib/cli.js check-coverage --branch 100 --statement 100"},"repository":{"type":"git","url":"git+https://github.com/NodeRedis/node-redis-parser.git"},"keywords":["redis","protocol","parser","database","javascript","node","nodejs","resp","hiredis"],"engines":{"node":">=0.10.0"},"devDependencies":{"benchmark":"^2.1.0","codeclimate-test-reporter":"^0.4.0","intercept-stdout":"^0.1.2","istanbul":"^0.4.0","standard":"^8.5.0","mocha":"^3.1.2","hiredis":"^0.5.0"},"author":{"name":"Ruben Bridgewater"},"license":"MIT","bugs":{"url":"https://github.com/NodeRedis/node-redis-parser/issues"},"homepage":"https://github.com/NodeRedis/node-redis-parser#readme","directories":{"test":"test","lib":"lib"},"gitHead":"94a3a4cb3d61118357cd7ff4e028b66a1edeebc9","_id":"redis-parser@2.2.0","_shasum":"4a01e162af66bd6eae7e6c291f9e25cb430351fa","_from":".","_npmVersion":"3.10.8","_nodeVersion":"7.0.0","_npmUser":{"name":"bridgear","email":"ruben@bridgewater.de"},"dist":{"shasum":"4a01e162af66bd6eae7e6c291f9e25cb430351fa","tarball":"https://registry.npmjs.org/redis-parser/-/redis-parser-2.2.0.tgz"},"maintainers":[{"name":"bridgear","email":"ruben@bridgewater.de"}],"_npmOperationalInternal":{"host":"packages-12-west.internal.npmjs.com","tmp":"tmp/redis-parser-2.2.0.tgz_1479484646654_0.18077522097155452"}},"2.3.0":{"name":"redis-parser","version":"2.3.0","description":"Javascript Redis protocol (RESP) parser","main":"index.js","scripts":{"test":"npm run coverage","benchmark":"node ./benchmark","posttest":"standard && npm run coverage:check","coverage":"node ./node_modules/istanbul/lib/cli.js cover --preserve-comments ./node_modules/mocha/bin/_mocha -- -R spec","coverage:check":"node ./node_modules/istanbul/lib/cli.js check-coverage --branch 100 --statement 100"},"repository":{"type":"git","url":"git+https://github.com/NodeRedis/node-redis-parser.git"},"keywords":["redis","protocol","parser","database","javascript","node","nodejs","resp","hiredis"],"engines":{"node":">=0.10.0"},"devDependencies":{"benchmark":"^2.1.0","codeclimate-test-reporter":"^0.4.0","intercept-stdout":"^0.1.2","istanbul":"^0.4.0","standard":"^8.5.0","mocha":"^3.1.2","hiredis":"^0.5.0"},"author":{"name":"Ruben Bridgewater"},"license":"MIT","bugs":{"url":"https://github.com/NodeRedis/node-redis-parser/issues"},"homepage":"https://github.com/NodeRedis/node-redis-parser#readme","directories":{"test":"test","lib":"lib"},"gitHead":"26be8f841e43afd4d1453ae21b55df129f2aa271","_id":"redis-parser@2.3.0","_shasum":"313a47965e49ee35ab3a86c93388b403d76237f6","_from":".","_npmVersion":"3.10.9","_nodeVersion":"7.1.0","_npmUser":{"name":"bridgear","email":"ruben@bridgewater.de"},"dist":{"shasum":"313a47965e49ee35ab3a86c93388b403d76237f6","tarball":"https://registry.npmjs.org/redis-parser/-/redis-parser-2.3.0.tgz"},"maintainers":[{"name":"bridgear","email":"ruben@bridgewater.de"}],"_npmOperationalInternal":{"host":"packages-18-east.internal.npmjs.com","tmp":"tmp/redis-parser-2.3.0.tgz_1480100588628_0.9477839153259993"}},"2.4.0":{"name":"redis-parser","version":"2.4.0","description":"Javascript Redis protocol (RESP) parser","main":"index.js","scripts":{"test":"npm run coverage","benchmark":"node ./benchmark","posttest":"standard && npm run coverage:check","coverage":"node ./node_modules/istanbul/lib/cli.js cover --preserve-comments ./node_modules/mocha/bin/_mocha -- -R spec","coverage:check":"node ./node_modules/istanbul/lib/cli.js check-coverage --branch 100 --statement 100"},"repository":{"type":"git","url":"git+https://github.com/NodeRedis/node-redis-parser.git"},"keywords":["redis","protocol","parser","database","javascript","node","nodejs","resp","hiredis"],"engines":{"node":">=0.10.0"},"devDependencies":{"benchmark":"^2.1.0","codeclimate-test-reporter":"^0.4.0","intercept-stdout":"^0.1.2","istanbul":"^0.4.0","standard":"^8.5.0","mocha":"^3.1.2","hiredis":"^0.5.0"},"author":{"name":"Ruben Bridgewater"},"license":"MIT","bugs":{"url":"https://github.com/NodeRedis/node-redis-parser/issues"},"homepage":"https://github.com/NodeRedis/node-redis-parser#readme","directories":{"test":"test","lib":"lib"},"gitHead":"c50cf5f0132ee993937588f221e64230688ec42d","_id":"redis-parser@2.4.0","_shasum":"018ea743077aae944d0b798b2fd12587320bf3c9","_from":".","_npmVersion":"4.0.5","_nodeVersion":"7.4.0","_npmUser":{"name":"bridgear","email":"ruben@bridgewater.de"},"dist":{"shasum":"018ea743077aae944d0b798b2fd12587320bf3c9","tarball":"https://registry.npmjs.org/redis-parser/-/redis-parser-2.4.0.tgz"},"maintainers":[{"name":"bridgear","email":"ruben@bridgewater.de"}],"_npmOperationalInternal":{"host":"packages-18-east.internal.npmjs.com","tmp":"tmp/redis-parser-2.4.0.tgz_1485363114604_0.7180071920156479"}},"2.5.0":{"name":"redis-parser","version":"2.5.0","description":"Javascript Redis protocol (RESP) parser","main":"index.js","scripts":{"test":"npm run coverage","benchmark":"node ./benchmark","lint":"standard --fix","posttest":"npm run lint && npm run coverage:check","coverage":"node ./node_modules/istanbul/lib/cli.js cover --preserve-comments ./node_modules/mocha/bin/_mocha -- -R spec","coverage:check":"node ./node_modules/istanbul/lib/cli.js check-coverage --branch 100 --statement 100"},"repository":{"type":"git","url":"git+https://github.com/NodeRedis/node-redis-parser.git"},"keywords":["redis","protocol","parser","database","javascript","node","nodejs","resp","hiredis"],"engines":{"node":">=0.10.0"},"devDependencies":{"benchmark":"^2.1.0","codeclimate-test-reporter":"^0.4.0","intercept-stdout":"^0.1.2","istanbul":"^0.4.0","standard":"^8.5.0","mocha":"^3.1.2","hiredis":"^0.5.0"},"author":{"name":"Ruben Bridgewater"},"license":"MIT","bugs":{"url":"https://github.com/NodeRedis/node-redis-parser/issues"},"homepage":"https://github.com/NodeRedis/node-redis-parser#readme","directories":{"test":"test","lib":"lib"},"gitHead":"d90fd064347f9ad38c4ff7db707098d8ec6bf83a","_id":"redis-parser@2.5.0","_shasum":"79fc2b1d4a6e4d2870b35368433639271fca2617","_from":".","_npmVersion":"4.1.2","_nodeVersion":"7.7.2","_npmUser":{"name":"bridgear","email":"ruben@bridgewater.de"},"dist":{"shasum":"79fc2b1d4a6e4d2870b35368433639271fca2617","tarball":"https://registry.npmjs.org/redis-parser/-/redis-parser-2.5.0.tgz"},"maintainers":[{"name":"bridgear","email":"ruben@bridgewater.de"}],"_npmOperationalInternal":{"host":"packages-12-west.internal.npmjs.com","tmp":"tmp/redis-parser-2.5.0.tgz_1489248893830_0.9956151561345905"}},"2.6.0":{"name":"redis-parser","version":"2.6.0","description":"Javascript Redis protocol (RESP) parser","main":"index.js","scripts":{"test":"npm run coverage","benchmark":"node ./benchmark","lint":"standard --fix","posttest":"npm run lint && npm run coverage:check","coverage":"node ./node_modules/istanbul/lib/cli.js cover --preserve-comments ./node_modules/mocha/bin/_mocha -- -R spec","coverage:check":"node ./node_modules/istanbul/lib/cli.js check-coverage --branch 100 --statement 100"},"repository":{"type":"git","url":"git+https://github.com/NodeRedis/node-redis-parser.git"},"keywords":["redis","protocol","parser","database","javascript","node","nodejs","resp","hiredis"],"engines":{"node":">=0.10.0"},"devDependencies":{"benchmark":"^2.1.0","codeclimate-test-reporter":"^0.4.0","intercept-stdout":"^0.1.2","istanbul":"^0.4.0","standard":"^9.0.0","mocha":"^3.1.2","hiredis":"^0.5.0"},"author":{"name":"Ruben Bridgewater"},"license":"MIT","bugs":{"url":"https://github.com/NodeRedis/node-redis-parser/issues"},"homepage":"https://github.com/NodeRedis/node-redis-parser#readme","directories":{"test":"test","lib":"lib"},"gitHead":"eea04cad0c4f53fd1e9f7079b5f4ededf50f5945","_id":"redis-parser@2.6.0","_shasum":"52ed09dacac108f1a631c07e9b69941e7a19504b","_from":".","_npmVersion":"4.1.2","_nodeVersion":"7.7.3","_npmUser":{"name":"bridgear","email":"ruben@bridgewater.de"},"dist":{"shasum":"52ed09dacac108f1a631c07e9b69941e7a19504b","tarball":"https://registry.npmjs.org/redis-parser/-/redis-parser-2.6.0.tgz"},"maintainers":[{"name":"bridgear","email":"ruben@bridgewater.de"}],"_npmOperationalInternal":{"host":"packages-12-west.internal.npmjs.com","tmp":"tmp/redis-parser-2.6.0.tgz_1491263124772_0.7531374620739371"}},"3.0.0":{"name":"redis-parser","version":"3.0.0","description":"Javascript Redis protocol (RESP) parser","main":"index.js","scripts":{"test":"npm run coverage","benchmark":"node ./benchmark","lint":"standard --fix","posttest":"npm run lint && npm run coverage:check","coverage":"node ./node_modules/istanbul/lib/cli.js cover --preserve-comments ./node_modules/mocha/bin/_mocha -- -R spec","coverage:check":"node ./node_modules/istanbul/lib/cli.js check-coverage --branch 100 --statement 100"},"repository":{"type":"git","url":"git+https://github.com/NodeRedis/node-redis-parser.git"},"keywords":["redis","protocol","parser","database","javascript","node","nodejs","resp","hiredis"],"engines":{"node":">=4"},"dependencies":{"redis-errors":"^1.0.0"},"devDependencies":{"benchmark":"^2.1.0","codeclimate-test-reporter":"^0.4.0","hiredis":"^0.5.0","istanbul":"^0.4.0","mocha":"^3.1.2","standard":"^10.0.0"},"author":{"name":"Ruben Bridgewater"},"license":"MIT","bugs":{"url":"https://github.com/NodeRedis/node-redis-parser/issues"},"homepage":"https://github.com/NodeRedis/node-redis-parser#readme","directories":{"test":"test","lib":"lib"},"gitHead":"701655430f5f7d9ca00892a02f7eefcbc1193a98","_id":"redis-parser@3.0.0","_shasum":"b66d828cdcafe6b4b8a428a7def4c6bcac31c8b4","_from":".","_npmVersion":"4.2.0","_nodeVersion":"7.10.0","_npmUser":{"name":"bridgear","email":"ruben@bridgewater.de"},"dist":{"shasum":"b66d828cdcafe6b4b8a428a7def4c6bcac31c8b4","tarball":"https://registry.npmjs.org/redis-parser/-/redis-parser-3.0.0.tgz"},"maintainers":[{"name":"bridgear","email":"ruben@bridgewater.de"}],"_npmOperationalInternal":{"host":"s3://npm-registry-packages","tmp":"tmp/redis-parser-3.0.0.tgz_1495738347528_0.7933312396053225"}}},"readme":"[![Build Status](https://travis-ci.org/NodeRedis/node-redis-parser.png?branch=master)](https://travis-ci.org/NodeRedis/node-redis-parser)\n[![Test Coverage](https://codeclimate.com/github/NodeRedis/node-redis-parser/badges/coverage.svg)](https://codeclimate.com/github/NodeRedis/node-redis-parser/coverage)\n[![js-standard-style](https://img.shields.io/badge/code%20style-standard-brightgreen.svg)](http://standardjs.com/)\n\n# redis-parser\n\nA high performance javascript redis parser built for [node_redis](https://github.com/NodeRedis/node_redis) and [ioredis](https://github.com/luin/ioredis). Parses all [RESP](http://redis.io/topics/protocol) data.\n\n## Install\n\nInstall with [NPM](https://npmjs.org/):\n\n    npm install redis-parser\n\n## Usage\n\n```js\nconst Parser = require('redis-parser');\n\nconst myParser = new Parser(options);\n```\n\n### Options\n\n* `returnReply`: *function*; mandatory\n* `returnError`: *function*; mandatory\n* `returnFatalError`: *function*; optional, defaults to the returnError function\n* `returnBuffers`: *boolean*; optional, defaults to false\n* `stringNumbers`: *boolean*; optional, defaults to false\n\n### Functions\n\n* `reset()`: reset the parser to it's initial state\n* `setReturnBuffers(boolean)`: set the returnBuffers option on/off without resetting the parser\n* `setStringNumbers(boolean)`: set the stringNumbers option on/off without resetting the parser\n\n### Error classes\n\n* `RedisError` sub class of Error\n* `ReplyError` sub class of RedisError\n* `ParserError` sub class of RedisError\n\nAll Redis errors will be returned as `ReplyErrors` while a parser error is returned as `ParserError`.  \nAll error classes can be imported by the npm `redis-errors` package.\n\n### Example\n\n```js\nconst Parser = require(\"redis-parser\");\n\nclass Library {\n  returnReply(reply) { /* ... */ }\n  returnError(err) { /* ... */ }\n  returnFatalError(err) { /* ... */ }\n\n  streamHandler() {\n    this.stream.on('data', (buffer) => {\n      // Here the data (e.g. `Buffer.from('$5\\r\\nHello\\r\\n'`))\n      // is passed to the parser and the result is passed to\n      // either function depending on the provided data.\n      parser.execute(buffer);\n    });\n  }\n}\n\nconst lib = new Library();\n\nconst parser = new Parser({\n  returnReply(reply) {\n    lib.returnReply(reply);\n  },\n  returnError(err) {\n    lib.returnError(err);\n  },\n  returnFatalError(err) {\n    lib.returnFatalError(err);\n  }\n});\n```\n\nYou do not have to use the returnFatalError function. Fatal errors will be returned in the normal error function in that case.\n\nAnd if you want to return buffers instead of strings, you can do this by adding the `returnBuffers` option.\n\nIf you handle with big numbers that are to large for JS (Number.MAX_SAFE_INTEGER === 2^53 - 16) please use the `stringNumbers` option. That way all numbers are going to be returned as String and you can handle them safely.\n\n```js\n// Same functions as in the first example\n\nconst parser = new Parser({\n  returnReply(reply) {\n    lib.returnReply(reply);\n  },\n  returnError(err) {\n    lib.returnError(err);\n  },\n  returnBuffers: true, // All strings are returned as Buffer e.g. <Buffer 48 65 6c 6c 6f>\n  stringNumbers: true // All numbers are returned as String\n});\n\n// The streamHandler as above\n```\n\n## Protocol errors\n\nTo handle protocol errors (this is very unlikely to happen) gracefully you should add the returnFatalError option, reject any still running command (they might have been processed properly but the reply is just wrong), destroy the socket and reconnect. Note that while doing this no new command may be added, so all new commands have to be buffered in the meantime, otherwise a chunk might still contain partial data of a following command that was already processed properly but answered in the same chunk as the command that resulted in the protocol error.\n\n## Contribute\n\nThe parser is highly optimized but there may still be further optimizations possible.\n\n    npm install\n    npm test\n    npm run benchmark\n\nCurrently the benchmark compares the performance against the hiredis parser:\n\n    HIREDIS:   $ multiple chunks in a bulk string x 994,387 ops/sec ±0.22% (554 runs sampled)\n    JS PARSER: $ multiple chunks in a bulk string x 1,010,728 ops/sec ±0.28% (559 runs sampled)\n    HIREDIS BUF:   $ multiple chunks in a bulk string x 648,742 ops/sec ±0.80% (526 runs sampled)\n    JS PARSER BUF: $ multiple chunks in a bulk string x 1,728,849 ops/sec ±0.41% (555 runs sampled)\n\n    HIREDIS:   + multiple chunks in a string x 1,861,132 ops/sec ±0.18% (564 runs sampled)\n    JS PARSER: + multiple chunks in a string x 2,131,892 ops/sec ±0.31% (558 runs sampled)\n    HIREDIS BUF:   + multiple chunks in a string x 965,132 ops/sec ±0.58% (521 runs sampled)\n    JS PARSER BUF: + multiple chunks in a string x 2,304,482 ops/sec ±0.31% (559 runs sampled)\n\n    HIREDIS:   $ 4mb bulk string x 269 ops/sec ±0.56% (452 runs sampled)\n    JS PARSER: $ 4mb bulk string x 763 ops/sec ±0.25% (466 runs sampled)\n    HIREDIS BUF:   $ 4mb bulk string x 336 ops/sec ±0.59% (459 runs sampled)\n    JS PARSER BUF: $ 4mb bulk string x 994 ops/sec ±0.36% (482 runs sampled)\n\n    HIREDIS:   + simple string x 2,504,305 ops/sec ±0.19% (563 runs sampled)\n    JS PARSER: + simple string x 5,121,952 ops/sec ±0.30% (560 runs sampled)\n    HIREDIS BUF:   + simple string x 1,122,899 ops/sec ±0.52% (516 runs sampled)\n    JS PARSER BUF: + simple string x 5,907,323 ops/sec ±0.23% (562 runs sampled)\n\n    HIREDIS:   : integer x 2,461,376 ops/sec ±0.14% (561 runs sampled)\n    JS PARSER: : integer x 18,543,688 ops/sec ±0.19% (539 runs sampled)\n    JS PARSER STR: : integer x 14,149,305 ops/sec ±0.24% (561 runs sampled)\n\n    HIREDIS:   : big integer x 2,114,270 ops/sec ±0.15% (561 runs sampled)\n    JS PARSER: : big integer x 10,794,439 ops/sec ±0.25% (560 runs sampled)\n    JS PARSER STR: : big integer x 4,594,807 ops/sec ±0.24% (558 runs sampled)\n\n    HIREDIS:   * array x 45,597 ops/sec ±0.23% (565 runs sampled)\n    JS PARSER: * array x 68,396 ops/sec ±0.30% (563 runs sampled)\n    HIREDIS BUF:   * array x 14,726 ops/sec ±0.39% (498 runs sampled)\n    JS PARSER BUF: * array x 80,961 ops/sec ±0.25% (561 runs sampled)\n\n    HIREDIS:   * big nested array x 212 ops/sec ±0.17% (511 runs sampled)\n    JS PARSER: * big nested array x 243 ops/sec ±0.21% (496 runs sampled)\n    HIREDIS BUF:   * big nested array x 207 ops/sec ±0.37% (430 runs sampled)\n    JS PARSER BUF: * big nested array x 297 ops/sec ±1.10% (421 runs sampled)\n\n    HIREDIS:   - error x 168,761 ops/sec ±0.28% (559 runs sampled)\n    JS PARSER: - error x 424,257 ops/sec ±0.28% (557 runs sampled)\n\n    Platform info:\n    Ubuntu 17.04\n    Node.js 7.10.0\n    Intel(R) Core(TM) i7-5600U CPU\n\n## License\n\n[MIT](./LICENSE)\n","maintainers":[{"name":"bridgear","email":"ruben@bridgewater.de"}],"time":{"modified":"2017-05-25T18:52:28.462Z","created":"2015-10-20T21:13:05.102Z","0.0.1":"2015-10-20T21:13:05.102Z","1.0.0":"2015-11-30T04:37:52.965Z","1.1.0":"2016-01-26T11:19:47.902Z","1.2.0":"2016-03-27T00:48:36.867Z","1.3.0":"2016-03-27T11:45:56.961Z","2.0.0":"2016-05-28T23:13:10.141Z","2.0.1":"2016-06-05T01:40:53.837Z","2.0.2":"2016-06-08T13:50:55.257Z","2.0.3":"2016-06-17T08:14:08.909Z","2.0.4":"2016-07-21T16:12:16.978Z","2.1.0":"2016-10-30T17:38:45.204Z","2.1.1":"2016-10-31T13:14:48.969Z","2.2.0":"2016-11-18T15:57:28.846Z","2.3.0":"2016-11-25T19:03:09.287Z","2.4.0":"2017-01-25T16:51:55.388Z","2.4.1":"2017-03-11T16:08:52.070Z","2.5.0":"2017-03-11T16:14:55.858Z","2.6.0":"2017-04-03T23:45:26.998Z","3.0.0":"2017-05-25T18:52:28.462Z"},"homepage":"https://github.com/NodeRedis/node-redis-parser#readme","keywords":["redis","protocol","parser","database","javascript","node","nodejs","resp","hiredis"],"repository":{"type":"git","url":"git+https://github.com/NodeRedis/node-redis-parser.git"},"author":{"name":"Ruben Bridgewater"},"bugs":{"url":"https://github.com/NodeRedis/node-redis-parser/issues"},"license":"MIT","readmeFilename":"README.md","users":{"xufz":true,"mojaray2k":true},"_attachments":{},"_etag":"W/\"592727ec-9489\"","_lastModified":"Thu, 25 May 2017 18:52:28 GMT","_cached":true}